B-Register/BRegister.v
`timescale 1ns/1ps

module BRegister(
    input [7:0]BusIn,
    input clk,rst,Bin,
    output [7:0]ALUIn
);

reg [7:0]temp;

always @(posedge clk or rst) begin
    if (rst == 1'b1)
    temp <= 8'b0000_0000;
    else if( Bin == 1'b1)
    temp <= BusIn;
end

assign ALUIn = temp ;



endmodule

B-Register/BRegisterTB.v
`timescale 1ns/1ps
`include "BRegister.v"

module tb;

    reg [7:0]BusIn ;
    reg clk,rst,Bin ;
    wire [7:0]ALUIn;

    BRegister dut(BusIn,clk,rst,Bin,ALUIn);

always #5 clk = ~clk ; 

initial begin

{BusIn,clk,Bin,rst} = 0;
$dumpfile("output.vcd");
$dumpvars(0,tb);

#100 $finish ; 

end

initial begin

    #12;
    rst <= 1;

    #7;
    rst <= 0;

    #1;
    BusIn <= 8'b0011_1010;
    
    #3;
    Bin <= 1;

    #11;
    rst <= 1;

    #4;
    rst <= 0;

end


endmodule

B-Register/output.vcd
$date
	Fri Jun 28 01:50:35 2024
$end
$version
	Icarus Verilog
$end
$timescale
	1ps
$end
$scope module tb $end
$var wire 8 ! ALUIn [7:0] $end
$var reg 1 " Bin $end
$var reg 8 # BusIn [7:0] $end
$var reg 1 $ clk $end
$var reg 1 % rst $end
$scope module dut $end
$var wire 8 & ALUIn [7:0] $end
$var wire 1 " Bin $end
$var wire 8 ' BusIn [7:0] $end
$var wire 1 $ clk $end
$var wire 1 % rst $end
$var reg 8 ( temp [7:0] $end
$upscope $end
$upscope $end
$enddefinitions $end
#0
$dumpvars
bx (
b0 '
bx &
0%
0$
b0 #
0"
bx !
$end
#5000
1$
#10000
0$
#12000
b0 !
b0 &
b0 (
1%
#15000
1$
#19000
0%
#20000
b111010 #
b111010 '
0$
#23000
1"
#25000
b111010 !
b111010 &
b111010 (
1$
#30000
0$
#34000
b0 !
b0 &
b0 (
1%
#35000
1$
#38000
b111010 !
b111010 &
b111010 (
0%
