RAM/RAM.v
`timescale 1ns/1ps

module RAM(
    input [7:0]BusIn,
    input [3:0]Addrs,
    input clk,RAMOut,RAMIn,
    output [7:0]BusOut
);

reg [7:0]temp[15:0];
reg [7:0]temp_out;

initial begin
    $readmemh("./Instructions.txt",temp,0,15);
end

always @(posedge clk or Addrs)
begin
    if (RAMIn == 1'b1)
    temp[Addrs] <= BusIn ;
    else 
    temp_out <= temp[Addrs];
end

assign BusOut = RAMOut ? temp_out : 8'bzzzz_zzzz ;


endmodule

RAM/RAMTB.v
`timescale 1ns/1ps
`include "RAM.v"

module tb;

reg [7:0]BusIn ;
reg [3:0]Addrs ;
reg clk,RAMOut,RAMIn ;
wire [7:0]BusOut ;
integer i;

RAM dut(BusIn,Addrs,clk,RAMOut,RAMIn,BusOut);

always #5 clk = ~clk ; 

initial begin
    {BusIn,Addrs,clk,RAMOut,RAMIn} <= 0 ;
    $dumpfile("output.vcd");
    $dumpvars(0,tb);
    #200 $finish ; 

end

initial begin

// Read Every Memory Word

for(i = 0; i < 16; i ++) begin

    #3;
    RAMOut <= 1;
    Addrs <= i ;
    #3;
    RAMOut <= 0;

    #4;


end

// Write into Memory 

Addrs <= 2;
BusIn <= 9;

#3;
RAMIn <= 1;
#4;
RAMIn <= 0;

#6;
RAMOut <= 1;






end



endmodule

RAM/output.vcd
$date
	Sun Jun 30 00:05:05 2024
$end
$version
	Icarus Verilog
$end
$timescale
	1ps
$end
$scope module tb $end
$var wire 8 ! BusOut [7:0] $end
$var reg 4 " Addrs [3:0] $end
$var reg 8 # BusIn [7:0] $end
$var reg 1 $ RAMIn $end
$var reg 1 % RAMOut $end
$var reg 1 & clk $end
$var integer 32 ' i [31:0] $end
$scope module dut $end
$var wire 4 ( Addrs [3:0] $end
$var wire 8 ) BusIn [7:0] $end
$var wire 1 $ RAMIn $end
$var wire 1 % RAMOut $end
$var wire 1 & clk $end
$var wire 8 * BusOut [7:0] $end
$var reg 8 + temp_out [7:0] $end
$upscope $end
$upscope $end
$enddefinitions $end
$comment Show the parameter values. $end
$dumpall
$end
#0
$dumpvars
b1110 +
bz *
b0 )
b0 (
b0 '
0&
0%
0$
b0 #
b0 "
bz !
$end
#3000
b1110 !
b1110 *
1%
#5000
1&
#6000
bz !
bz *
0%
#10000
b1 '
0&
#13000
b11110001 +
b11110001 !
b11110001 *
b1 "
b1 (
1%
#15000
1&
#16000
bz !
bz *
0%
#20000
b10 '
0&
#23000
b101101 +
b101101 !
b101101 *
b10 "
b10 (
1%
#25000
1&
#26000
bz !
bz *
0%
#30000
b11 '
0&
#33000
b11100000 +
b11100000 !
b11100000 *
b11 "
b11 (
1%
#35000
1&
#36000
bz !
bz *
0%
#40000
b100 '
0&
#43000
b11110000 +
b11110000 !
b11110000 *
b100 "
b100 (
1%
#45000
1&
#46000
bz !
bz *
0%
#50000
b101 '
0&
#53000
b0 +
b0 !
b0 *
b101 "
b101 (
1%
#55000
1&
#56000
bz !
bz *
0%
#60000
b110 '
0&
#63000
b0 !
b0 *
b110 "
b110 (
1%
#65000
1&
#66000
bz !
bz *
0%
#70000
b111 '
0&
#73000
b0 !
b0 *
b111 "
b111 (
1%
#75000
1&
#76000
bz !
bz *
0%
#80000
b1000 '
0&
#83000
b0 !
b0 *
b1000 "
b1000 (
1%
#85000
1&
#86000
bz !
bz *
0%
#90000
b1001 '
0&
#93000
b0 !
b0 *
b1001 "
b1001 (
1%
#95000
1&
#96000
bz !
bz *
0%
#100000
b1010 '
0&
#103000
b0 !
b0 *
b1010 "
b1010 (
1%
#105000
1&
#106000
bz !
bz *
0%
#110000
b1011 '
0&
#113000
b0 !
b0 *
b1011 "
b1011 (
1%
#115000
1&
#116000
bz !
bz *
0%
#120000
b1100 '
0&
#123000
b0 !
b0 *
b1100 "
b1100 (
1%
#125000
1&
#126000
bz !
bz *
0%
#130000
b1101 '
0&
#133000
b1010 +
b1010 !
b1010 *
b1101 "
b1101 (
1%
#135000
1&
#136000
bz !
bz *
0%
#140000
b1110 '
0&
#143000
b1010 !
b1010 *
b1110 "
b1110 (
1%
#145000
1&
#146000
bz !
bz *
0%
#150000
b1111 '
0&
#153000
b1110 +
b1110 !
b1110 *
b1111 "
b1111 (
1%
#155000
1&
#156000
bz !
bz *
0%
#160000
b101101 +
b1001 #
b1001 )
b10 "
b10 (
b10000 '
0&
#163000
1$
#165000
1&
#167000
0$
#170000
0&
#173000
b101101 !
b101101 *
1%
#175000
b1001 !
b1001 *
b1001 +
1&
