Output-Register/OutputRegister.v
`timescale 1ns/1ps

module OutputReg(
    input [7:0]BusIn,
    input clk,rst,OutLoad,
    output [7:0]Out
);

reg [7:0]temp;

always @(posedge clk or rst) begin

    if( rst == 1'b1 )
    temp <= 8'b0000_0000;
    else if(OutLoad ==1'b1)
    temp <= BusIn ;
    
end

assign Out = temp ;


endmodule

Output-Register/OutputRegisterTB.v
`timescale 1ns/1ps
`include "OutputRegister.v"

module tb;


    reg[7:0]BusIn;
    reg clk,rst,OutLoad;
    wire [7:0]Out;

OutputReg dut(BusIn,clk,rst,OutLoad,Out);

always #5 clk = ~clk ; 

initial begin
    {BusIn,clk,rst,OutLoad} <= 0 ;
    $dumpfile("output.vcd");
    $dumpvars(0,tb);
    #100 $finish ; 

end

initial begin

    #2;
    rst <= 1;

    #4;
    rst <= 0;

    #1;
    BusIn <= 8'b0101_1100;

    #2;
    OutLoad <= 1;

    #7;
    BusIn <= 8'b0011_1100;

    #2;
    OutLoad <= 0;

    #6;
    OutLoad <= 1;

    #5;
    OutLoad <= 0;


end

endmodule

Output-Register/output.vcd
$date
	Sat Jun 29 01:34:37 2024
$end
$version
	Icarus Verilog
$end
$timescale
	1ps
$end
$scope module tb $end
$var wire 8 ! Out [7:0] $end
$var reg 8 " BusIn [7:0] $end
$var reg 1 # OutLoad $end
$var reg 1 $ clk $end
$var reg 1 % rst $end
$scope module dut $end
$var wire 8 & BusIn [7:0] $end
$var wire 8 ' Out [7:0] $end
$var wire 1 # OutLoad $end
$var wire 1 $ clk $end
$var wire 1 % rst $end
$var reg 8 ( temp [7:0] $end
$upscope $end
$upscope $end
$enddefinitions $end
$comment Show the parameter values. $end
$dumpall
$end
#0
$dumpvars
bx (
bx '
b0 &
0%
0$
0#
b0 "
bx !
$end
#2000
b0 !
b0 '
b0 (
1%
#5000
1$
#6000
0%
#7000
b1011100 "
b1011100 &
#9000
1#
#10000
0$
#15000
b1011100 !
b1011100 '
b1011100 (
1$
#16000
b111100 "
b111100 &
#18000
0#
#20000
0$
#24000
1#
#25000
b111100 !
b111100 '
b111100 (
1$
#29000
0#
