CPU/CPU.v
`timescale 1ns/1ps

`define LDA  4'b0000
`define STA  4'b0001
`define ADD  4'b0010
`define SUB  4'b0011
`define INCA 4'b0100
`define DECR 4'b0101
`define JMPZ 4'b0110
`define NOP  4'b0111
`define JMP  4'b1000
`define JMPC 4'b1001
`define LDI  4'b1010
`define OUT  4'b1011
`define HLT  4'b1100

`define ALU_ADD 2'b00
`define ALU_SUB 2'b01
`define ALU_INC 2'b10
`define ALU_DCR 2'b11



module CPU(
    input rst,clk

);

wire [7:0]Bus,AccumulatorToAlu,BRegisterToALU,Finaloutput;
wire [3:0]MarToRam,IrToCu;
wire [17:0]CS;
wire [1:0]FlagToCU,AluFlagToFlagReg;

PC dutPC(Bus[3:0], clk,rst,CS[4],CS[3],CS[2],Bus[3:0]);
Accumulator dutAcc(Bus,clk,rst,CS[12],CS[11],CS[10],Bus,AccumulatorToAlu);
MAR dutMar(Bus[3:0],clk,rst,CS[6],MarToRam);
ALU dutALU(AccumulatorToAlu,BRegisterToALU,{CS[14],CS[13]},CS[15],CS[17],Bus,AluFlagToFlagReg);
RAM dutRAM(Bus,MarToRam,clk,CS[1],CS[0],Bus);
BRegister dutBReg(Bus,clk,rst,CS[9],BRegisterToALU);
IR dutReg(Bus,clk,rst,CS[8],CS[7],Bus[3:0],IrToCu);
OutputReg dutOutputReg(Bus,clk,rst,CS[5],Finaloutput);
controlunit dutCU(IrToCu,FlagToCU,clk,rst,CS);
FlagRegister dutFlagReg(AluFlagToFlagReg,CS[17],CS[16],clk,FlagToCU);


endmodule



module controlunit(
    input [3:0]opcode,
    input [1:0]flagReg,
    input clk,rst,
    output [17:0]ControlSignal
);

// Micro Opertions 
parameter idle = 0 ;
// Fetch States
parameter  fetch1 = 1;
parameter  fetch2 = 2; // Internall this state also performs Instruction Decode
                       // Because of Common Bus Architecture
// Load States
parameter  lda1 = 3;
parameter  lda2 = 4;
// Add States
parameter  add1 = 5;
parameter  add2 = 6;
parameter  add3 = 7;
// Subtract States
parameter  sub1 = 8;
parameter  sub2 = 9;
parameter  sub3 = 10;
// Output State
parameter  out  = 11;
// Halt State
parameter  hlt1  = 12;
// Increment States
parameter inc1 = 13;
parameter inc2 = 14;
// Decrement States
parameter dec1 = 15;
parameter dec2 = 16;
// No-Operation State : No additional State is Required : Fetch 1 & 2 are enough

// Store States
parameter sta1 = 17;
parameter sta2 = 18;

// Jump States
parameter jmp1 = 19;

// Jump if Zero States
parameter jmpz1 = 20;
parameter jmpz2 = 21;

// Jump if Carry States
parameter jmpc1 = 22;
parameter jmpc2 = 23;

// Load Immediate States
parameter ldi1 = 24;



reg [17:0]temp ;

reg [4:0]state,nstate;

always @(negedge clk ) begin
    if(rst == 1'b1)
    state <= idle;
    else
    state <= nstate;
end

always@(state) begin
    case(state)
    idle :   temp <= 0 ;
    fetch1 : temp <= 18'h00048;
    fetch2 : temp <= 18'h00112;

    lda1   : temp <= 18'h000C0;
    lda2   : temp <= 18'h01002;

    add1   : temp <= 18'h000C0;
    add2   : temp <= 18'h20202;
    add3   : temp <= 18'h09000;

    sub1   : temp <= 18'h000C0;
    sub2   : temp <= 18'h22202;
    sub3   : temp <= 18'h09000;

    out    : temp <= 18'h00420;

    hlt1   : temp <= 18'h00000;

    inc1   : temp <= 18'h24000;
    inc2   : temp <= 18'h09000;

    dec1   : temp <= 18'h26000;
    dec2   : temp <= 18'h09000;

    sta1   : temp <= 18'h000C0;
    sta2   : temp <= 18'h00401;

    jmp1   : temp <= 18'h00084;

    jmpz1  : temp <= 18'h10000;
    jmpz2  : temp <= 18'h00084;

    jmpc1  : temp <= 18'h10000;
    jmpc2  : temp <= 18'h00084;

    ldi1   : temp <= 18'h00880;

    default : temp <= 0;

    endcase

end



always @(state,opcode,flagReg)begin
    case(state)
    idle : begin
        nstate = fetch1 ;
    end
    fetch1 : begin
        nstate = fetch2 ;
    end
    fetch2 : begin
        case(opcode)
        `LDA : nstate = lda1 ;
        `ADD : nstate = add1 ;
        `SUB : nstate = sub1 ;
        `OUT : nstate = out ;
        `HLT : nstate = hlt1 ;
        `STA : nstate = sta1;
        `INCA: nstate = inc1;
        `DECR: nstate = dec1;
        `JMP : nstate = jmp1 ;
        `JMPZ: nstate = jmpz1;
        `JMPC: nstate = jmpc1;
        `NOP : nstate = fetch1;
        `LDI : nstate = ldi1 ;
        default: nstate = idle;
       endcase

    end
    lda1 : begin
        nstate = lda2 ;

    end
    lda2 : begin
        nstate = fetch1 ;
    end
    add1 : begin
        nstate = add2;

    end
    add2 : begin
        nstate = add3 ;

    end
    add3 : begin
        nstate = fetch1;
    end
    sub1 : begin
        nstate = sub2;
    end
    sub2 : begin
        nstate = sub3 ;
    end
    sub3 : begin
        nstate = fetch1;
    end

    out : begin
        nstate = fetch1;
    end

    hlt1 : begin
        if(rst == 1'b1)
        nstate = idle;
        else 
        nstate = hlt1 ;
    end

    sta1 : begin
        nstate = sta2;
    end
    sta2 : begin
        nstate = fetch1;
    end

    inc1 : begin 
        nstate = inc2 ;
    end
    inc2 : begin
        nstate = fetch1;
    end

    dec1 : begin
        nstate = dec2 ;
    end
    dec2 : begin
        nstate = fetch1;
    end

    jmp1 : begin
        nstate = fetch1 ;
    end
    jmpz1: begin
        if(flagReg[1] == 1'b1)
        nstate = jmpz2;
        else
        nstate = fetch1 ;
    end

    jmpz2 : begin
        nstate = fetch1;
    end
    jmpc1: begin
        if(flagReg[0] == 1'b1)
        nstate = jmpc2;
        else
        nstate = fetch1 ;
    end
    jmpc2 : begin
        nstate = fetch1;
    end
    
    ldi1 : begin
        nstate = fetch1;

    end

    default : nstate = idle ;

    endcase
    
end

assign ControlSignal = temp ;



endmodule



module FlagRegister(
    input [1:0]FlagsIn,
    input FlagEnable,
    input FlagOutEnable,
    input clk,
    output [1:0]FlagOut 
);

reg [1:0]temp;

always @(posedge clk ) begin
    if(FlagEnable ==1'b1)
    temp <= FlagsIn ;
end
assign FlagOut = FlagOutEnable ? temp: 2'bzz;


endmodule



module IR(
    input [7:0]BusIn,
    input clk,rst,IRIn,IROut,
    output [3:0]BusOut,CUIn
);

reg [7:0]temp;

always @(posedge clk or rst) begin

    if (rst == 1'b1)
    temp <= 8'b0000_0000;
    else if( IRIn == 1'b1)
    temp <= BusIn ;
end

assign CUIn = temp[7:4];
assign BusOut = IROut? temp[3:0] : 4'bzzzz ;


endmodule

module MAR(
    input [3:0]BusIn,
    input clk,rst,MARIn,
    output [3:0]RAMIn
);

reg [3:0]temp;

always @(posedge clk or rst ) begin

    if (rst == 1'b1)
    temp <= 4'b0000;
    else if (MARIn == 1'b1)
    temp <= BusIn ;
  
end


    assign RAMIn = temp ;

endmodule


module BRegister(
    input [7:0]BusIn,
    input clk,rst,Bin,
    output [7:0]ALUIn
);

reg [7:0]temp;

always @(posedge clk or rst) begin
    if (rst == 1'b1)
    temp <= 8'b0000_0000;
    else if( Bin == 1'b1)
    temp <= BusIn;
end

assign ALUIn = temp ;



endmodule

module Accumulator(
    input [7:0]BusIn,
    input clk,rst,Ain,ALowerIn,Aout,
    output [7:0]BusOut,ALUIn
);

reg [7:0]temp;
always @(posedge clk,rst) begin
    if(rst == 1'b1)
    temp <= 8'b0000_0000;
    else if (Ain == 1'b1)
    temp <= BusIn ;
    else if (ALowerIn == 1'b1)
    temp <= {4'b0000,BusIn[3:0]};

end

assign BusOut = Aout ? temp : 8'bzzzz_zzzz;
assign ALUIn  = temp ; 
    

endmodule




module RAM(
    input [7:0]BusIn,
    input [3:0]Addrs,
    input clk,RAMOut,RAMIn,
    output [7:0]BusOut
);

reg [7:0]temp[15:0];
reg [7:0]temp_out;

initial begin
    $readmemh("./Instructions.txt",temp,0,15);
end

always @(posedge clk or Addrs)
begin
    if (RAMIn == 1'b1)
    temp[Addrs] <= BusIn ;
    else 
    temp_out <= temp[Addrs];
end

assign BusOut = RAMOut ? temp_out : 8'bzzzz_zzzz ;


endmodule



module PC(
    input [3:0]BusIn,
    input clk,rst,PCInc,PCOut,PCIn,
    output [3:0]BusOut
);

reg [3:0]temp;

always @(posedge clk or rst) begin

    if(rst ==1'b1)
    temp <= 4'b0000;
    else if(PCInc == 1'b1)
    temp <= temp + 1;
    else if(PCIn == 1'b1)
    temp <= BusIn;

end

assign BusOut = PCOut ? temp : 4'bzzzz;



endmodule 





module ALU(
    input [7:0]Accumulator,BRegister,
    input [1:0]Operation,
    input ALUOut,AluStart,
    output [7:0]BusOut,
    output [1:0]Flags
);

reg [8:0]result;
 
always @(*)begin

    if(AluStart == 1'b1)
    begin
    case(Operation) 
    `ALU_ADD : result <= Accumulator + BRegister ;
    `ALU_SUB : result <= Accumulator - BRegister ;
    `ALU_INC : result <= Accumulator + 1 ;
    `ALU_DCR : result <= Accumulator - 1 ;
    default : result <= result ;

    endcase


    end

end


assign BusOut = ALUOut ? result[7:0] : 8'bzzzz_zzzz;
assign Flags = {~|result[7:0],result[8]};  // Zero,Carry


endmodule



module OutputReg(
    input [7:0]BusIn,
    input clk,rst,OutLoad,
    output [7:0]Out
);

reg [7:0]temp;

always @(posedge clk or rst) begin

    if( rst == 1'b1 )
    temp <= 8'b0000_0000;
    else if(OutLoad ==1'b1)
    temp <= BusIn ;
    
end

assign Out = temp ;


endmodule

CPU/CPUTB.v
`timescale 1ns/1ps
`include "CPU.v"

module tb;

reg rst,clk;

CPU dut(rst,clk);

always #5 clk = ~clk ; 

initial begin
    {rst,clk} <= 0; 
    $dumpfile("output.vcd");
    $dumpvars(0,tb);
    #100000 $finish ;     // Change According to the needs
end

initial begin

rst <= 1 ; 
#17;
rst <= 0 ;

end


endmodule

CPU/output.vcd
$date
	Sat Jul  6 22:29:55 2024
$end
$version
	Icarus Verilog
$end
$timescale
	1ps
$end
$scope module tb $end
$var reg 1 ! clk $end
$var reg 1 " rst $end
$scope module dut $end
$var wire 8 # Bus [7:0] $end
$var wire 1 ! clk $end
$var wire 1 " rst $end
$var wire 4 $ MarToRam [3:0] $end
$var wire 4 % IrToCu [3:0] $end
$var wire 2 & FlagToCU [1:0] $end
$var wire 8 ' Finaloutput [7:0] $end
$var wire 18 ( CS [17:0] $end
$var wire 8 ) BRegisterToALU [7:0] $end
$var wire 2 * AluFlagToFlagReg [1:0] $end
$var wire 8 + AccumulatorToAlu [7:0] $end
$scope module dutALU $end
$var wire 1 , ALUOut $end
$var wire 1 - AluStart $end
$var wire 8 . BusOut [7:0] $end
$var wire 2 / Operation [1:0] $end
$var wire 2 0 Flags [1:0] $end
$var wire 8 1 BRegister [7:0] $end
$var wire 8 2 Accumulator [7:0] $end
$var reg 9 3 result [8:0] $end
$upscope $end
$scope module dutAcc $end
$var wire 8 4 ALUIn [7:0] $end
$var wire 1 5 ALowerIn $end
$var wire 1 6 Ain $end
$var wire 1 7 Aout $end
$var wire 8 8 BusIn [7:0] $end
$var wire 8 9 BusOut [7:0] $end
$var wire 1 ! clk $end
$var wire 1 " rst $end
$var reg 8 : temp [7:0] $end
$upscope $end
$scope module dutBReg $end
$var wire 8 ; ALUIn [7:0] $end
$var wire 1 < Bin $end
$var wire 8 = BusIn [7:0] $end
$var wire 1 ! clk $end
$var wire 1 " rst $end
$var reg 8 > temp [7:0] $end
$upscope $end
$scope module dutCU $end
$var wire 1 ! clk $end
$var wire 1 " rst $end
$var wire 4 ? opcode [3:0] $end
$var wire 2 @ flagReg [1:0] $end
$var wire 18 A ControlSignal [17:0] $end
$var parameter 32 B add1 $end
$var parameter 32 C add2 $end
$var parameter 32 D add3 $end
$var parameter 32 E dec1 $end
$var parameter 32 F dec2 $end
$var parameter 32 G fetch1 $end
$var parameter 32 H fetch2 $end
$var parameter 32 I hlt1 $end
$var parameter 32 J idle $end
$var parameter 32 K inc1 $end
$var parameter 32 L inc2 $end
$var parameter 32 M jmp1 $end
$var parameter 32 N jmpc1 $end
$var parameter 32 O jmpc2 $end
$var parameter 32 P jmpz1 $end
$var parameter 32 Q jmpz2 $end
$var parameter 32 R lda1 $end
$var parameter 32 S lda2 $end
$var parameter 32 T ldi1 $end
$var parameter 32 U out $end
$var parameter 32 V sta1 $end
$var parameter 32 W sta2 $end
$var parameter 32 X sub1 $end
$var parameter 32 Y sub2 $end
$var parameter 32 Z sub3 $end
$var reg 5 [ nstate [4:0] $end
$var reg 5 \ state [4:0] $end
$var reg 18 ] temp [17:0] $end
$upscope $end
$scope module dutFlagReg $end
$var wire 1 ^ FlagEnable $end
$var wire 1 _ FlagOutEnable $end
$var wire 2 ` FlagsIn [1:0] $end
$var wire 1 ! clk $end
$var wire 2 a FlagOut [1:0] $end
$var reg 2 b temp [1:0] $end
$upscope $end
$scope module dutMar $end
$var wire 4 c BusIn [3:0] $end
$var wire 1 d MARIn $end
$var wire 4 e RAMIn [3:0] $end
$var wire 1 ! clk $end
$var wire 1 " rst $end
$var reg 4 f temp [3:0] $end
$upscope $end
$scope module dutOutputReg $end
$var wire 8 g BusIn [7:0] $end
$var wire 8 h Out [7:0] $end
$var wire 1 i OutLoad $end
$var wire 1 ! clk $end
$var wire 1 " rst $end
$var reg 8 j temp [7:0] $end
$upscope $end
$scope module dutPC $end
$var wire 4 k BusIn [3:0] $end
$var wire 1 l PCIn $end
$var wire 1 m PCInc $end
$var wire 1 n PCOut $end
$var wire 1 ! clk $end
$var wire 1 " rst $end
$var wire 4 o BusOut [3:0] $end
$var reg 4 p temp [3:0] $end
$upscope $end
$scope module dutRAM $end
$var wire 4 q Addrs [3:0] $end
$var wire 8 r BusIn [7:0] $end
$var wire 8 s BusOut [7:0] $end
$var wire 1 t RAMIn $end
$var wire 1 u RAMOut $end
$var wire 1 ! clk $end
$var reg 8 v temp_out [7:0] $end
$upscope $end
$scope module dutReg $end
$var wire 8 w BusIn [7:0] $end
$var wire 1 x IRIn $end
$var wire 1 y IROut $end
$var wire 1 ! clk $end
$var wire 1 " rst $end
$var wire 4 z CUIn [3:0] $end
$var wire 4 { BusOut [3:0] $end
$var reg 8 | temp [7:0] $end
$upscope $end
$upscope $end
$upscope $end
$enddefinitions $end
$comment Show the parameter values. $end
$dumpall
b1010 Z
b1001 Y
b1000 X
b10010 W
b10001 V
b1011 U
b11000 T
b100 S
b11 R
b10101 Q
b10100 P
b10111 O
b10110 N
b10011 M
b1110 L
b1101 K
b0 J
b1100 I
b10 H
b1 G
b10000 F
b1111 E
b111 D
b110 C
b101 B
$end
#0
$dumpvars
b0 |
bz {
b0 z
0y
0x
bz w
b10110000 v
0u
0t
bz s
bz r
b0 q
b0 p
bz o
0n
0m
0l
bz k
b0 j
0i
b0 h
bz g
b0 f
b0 e
0d
bz c
bx b
bz a
bx `
0_
0^
b0 ]
b0 \
b1 [
b0 A
bz @
b0 ?
b0 >
bz =
0<
b0 ;
b0 :
bz 9
bz 8
07
06
05
b0 4
bx 3
b0 2
b0 1
bx 0
b0 /
bz .
0-
0,
b0 +
bx *
b0 )
b0 (
b0 '
bz &
b0 %
b0 $
bz #
1"
0!
$end
#5000
1!
#10000
0!
#15000
1!
#17000
0"
#20000
b0 k
b0 c
bz0000 #
bz0000 .
bz0000 8
bz0000 9
bz0000 =
bz0000 g
bz0000 r
bz0000 s
bz0000 w
b0 o
1d
1n
b1001000 (
b1001000 A
b1001000 ]
b10 [
b1 \
0!
#25000
1!
#30000
b10110000 #
b10110000 .
b10110000 8
b10110000 9
b10110000 =
b10110000 g
b10110000 r
b10110000 s
b10110000 w
bz o
1x
1u
0d
0n
1m
b100010010 (
b100010010 A
b100010010 ]
b11 [
b10 \
0!
#35000
b1011 [
b1011 %
b1011 ?
b1011 z
b10110000 |
b1 p
1!
#40000
b0 #
b0 .
b0 8
b0 9
b0 =
b0 g
b0 r
b0 s
b0 w
1i
0x
0u
17
0m
b10000100000 (
b10000100000 A
b10000100000 ]
b1 [
b1011 \
0!
#45000
1!
#50000
b1 k
b1 c
bz0001 #
bz0001 .
bz0001 8
bz0001 9
bz0001 =
bz0001 g
bz0001 r
bz0001 s
bz0001 w
b1 o
0i
1d
07
1n
b1001000 (
b1001000 A
b1001000 ]
b10 [
b1 \
0!
#55000
b1000000 v
b1 $
b1 e
b1 q
b1 f
1!
#60000
b0 k
b0 c
b1000000 #
b1000000 .
b1000000 8
b1000000 9
b1000000 =
b1000000 g
b1000000 r
b1000000 s
b1000000 w
bz o
1x
1u
0d
0n
1m
b100010010 (
b100010010 A
b100010010 ]
b1011 [
b10 \
0!
#65000
b1101 [
b100 %
b100 ?
b100 z
b10 p
b1000000 |
1!
#70000
b0 *
b0 0
b0 `
b1 3
bz k
bz c
bz #
bz .
bz 8
bz 9
bz =
bz g
bz r
bz s
bz w
1^
0x
0u
1-
b10 /
0m
b100100000000000000 (
b100100000000000000 A
b100100000000000000 ]
b1110 [
b1101 \
0!
#75000
b0 b
1!
#80000
b1 k
b1 c
b1 #
b1 .
b1 8
b1 9
b1 =
b1 g
b1 r
b1 s
b1 w
0^
0-
1,
b0 /
16
b1001000000000000 (
b1001000000000000 A
b1001000000000000 ]
b1 [
b1110 \
0!
#85000
b1 +
b1 2
b1 4
b1 :
1!
#90000
b10 k
b10 c
bz0010 #
bz0010 .
bz0010 8
bz0010 9
bz0010 =
bz0010 g
bz0010 r
bz0010 s
bz0010 w
b10 o
0,
1d
06
1n
b1001000 (
b1001000 A
b1001000 ]
b10 [
b1 \
0!
#95000
b10010100 v
b10 $
b10 e
b10 q
b10 f
1!
#100000
b100 k
b100 c
b10010100 #
b10010100 .
b10010100 8
b10010100 9
b10010100 =
b10010100 g
b10010100 r
b10010100 s
b10010100 w
bz o
1x
1u
0d
0n
1m
b100010010 (
b100010010 A
b100010010 ]
b1101 [
b10 \
0!
#105000
b10110 [
b1001 %
b1001 ?
b1001 z
b11 p
b10010100 |
1!
#110000
bz k
bz c
b0 &
b0 @
b0 a
bz #
bz .
bz 8
bz 9
bz =
bz g
bz r
bz s
bz w
1_
0x
0u
0m
b10000000000000000 (
b10000000000000000 A
b10000000000000000 ]
b1 [
b10110 \
0!
#115000
1!
#120000
b11 k
b11 c
bz &
bz @
bz a
bz0011 #
bz0011 .
bz0011 8
bz0011 9
bz0011 =
bz0011 g
bz0011 r
bz0011 s
bz0011 w
b11 o
0_
1d
1n
b1001000 (
b1001000 A
b1001000 ]
b10 [
b1 \
0!
#125000
b10000000 v
b11 $
b11 e
b11 q
b11 f
1!
#130000
b0 k
b0 c
b10000000 #
b10000000 .
b10000000 8
b10000000 9
b10000000 =
b10000000 g
b10000000 r
b10000000 s
b10000000 w
bz o
1x
1u
0d
0n
1m
b100010010 (
b100010010 A
b100010010 ]
b10110 [
b10 \
0!
#135000
b10011 [
b1000 %
b1000 ?
b1000 z
b10000000 |
b100 p
1!
#140000
b0 {
bz0000 #
bz0000 .
bz0000 8
bz0000 9
bz0000 =
bz0000 g
bz0000 r
bz0000 s
bz0000 w
1y
0x
0u
1l
0m
b10000100 (
b10000100 A
b10000100 ]
b1 [
b10011 \
0!
#145000
b0 p
1!
#150000
bz {
b0 o
0y
1d
0l
1n
b1001000 (
b1001000 A
b1001000 ]
b10 [
b1 \
0!
#155000
b10110000 v
b0 $
b0 e
b0 q
b0 f
1!
#160000
b10110000 #
b10110000 .
b10110000 8
b10110000 9
b10110000 =
b10110000 g
b10110000 r
b10110000 s
b10110000 w
bz o
1x
1u
0d
0n
1m
b100010010 (
b100010010 A
b100010010 ]
b10011 [
b10 \
0!
#165000
b1011 [
b1011 %
b1011 ?
b1011 z
b1 p
b10110000 |
1!
#170000
b1 k
b1 c
b1 #
b1 .
b1 8
b1 9
b1 =
b1 g
b1 r
b1 s
b1 w
1i
0x
0u
17
0m
b10000100000 (
b10000100000 A
b10000100000 ]
b1 [
b1011 \
0!
#175000
b1 '
b1 h
b1 j
1!
#180000
bz0001 #
bz0001 .
bz0001 8
bz0001 9
bz0001 =
bz0001 g
bz0001 r
bz0001 s
bz0001 w
b1 o
0i
1d
07
1n
b1001000 (
b1001000 A
b1001000 ]
b10 [
b1 \
0!
#185000
b1000000 v
b1 $
b1 e
b1 q
b1 f
1!
#190000
b0 k
b0 c
b1000000 #
b1000000 .
b1000000 8
b1000000 9
b1000000 =
b1000000 g
b1000000 r
b1000000 s
b1000000 w
bz o
1x
1u
0d
0n
1m
b100010010 (
b100010010 A
b100010010 ]
b1011 [
b10 \
0!
#195000
b1101 [
b100 %
b100 ?
b100 z
b1000000 |
b10 p
1!
#200000
b10 3
bz k
bz c
bz #
bz .
bz 8
bz 9
bz =
bz g
bz r
bz s
bz w
1^
0x
0u
1-
b10 /
0m
b100100000000000000 (
b100100000000000000 A
b100100000000000000 ]
b1110 [
b1101 \
0!
#205000
1!
#210000
b10 k
b10 c
b10 #
b10 .
b10 8
b10 9
b10 =
b10 g
b10 r
b10 s
b10 w
0^
0-
1,
b0 /
16
b1001000000000000 (
b1001000000000000 A
b1001000000000000 ]
b1 [
b1110 \
0!
#215000
b10 +
b10 2
b10 4
b10 :
1!
#220000
bz0010 #
bz0010 .
bz0010 8
bz0010 9
bz0010 =
bz0010 g
bz0010 r
bz0010 s
bz0010 w
b10 o
0,
1d
06
1n
b1001000 (
b1001000 A
b1001000 ]
b10 [
b1 \
0!
#225000
b10010100 v
b10 $
b10 e
b10 q
b10 f
1!
#230000
b100 k
b100 c
b10010100 #
b10010100 .
b10010100 8
b10010100 9
b10010100 =
b10010100 g
b10010100 r
b10010100 s
b10010100 w
bz o
1x
1u
0d
0n
1m
b100010010 (
b100010010 A
b100010010 ]
b1101 [
b10 \
0!
#235000
b10110 [
b1001 %
b1001 ?
b1001 z
b10010100 |
b11 p
1!
#240000
bz k
bz c
b0 &
b0 @
b0 a
bz #
bz .
bz 8
bz 9
bz =
bz g
bz r
bz s
bz w
1_
0x
0u
0m
b10000000000000000 (
b10000000000000000 A
b10000000000000000 ]
b1 [
b10110 \
0!
#245000
1!
#250000
b11 k
b11 c
bz &
bz @
bz a
bz0011 #
bz0011 .
bz0011 8
bz0011 9
bz0011 =
bz0011 g
bz0011 r
bz0011 s
bz0011 w
b11 o
0_
1d
1n
b1001000 (
b1001000 A
b1001000 ]
b10 [
b1 \
0!
#255000
b10000000 v
b11 $
b11 e
b11 q
b11 f
1!
#260000
b0 k
b0 c
b10000000 #
b10000000 .
b10000000 8
b10000000 9
b10000000 =
b10000000 g
b10000000 r
b10000000 s
b10000000 w
bz o
1x
1u
0d
0n
1m
b100010010 (
b100010010 A
b100010010 ]
b10110 [
b10 \
0!
#265000
b10011 [
b1000 %
b1000 ?
b1000 z
b100 p
b10000000 |
1!
#270000
b0 {
bz0000 #
bz0000 .
bz0000 8
bz0000 9
bz0000 =
bz0000 g
bz0000 r
bz0000 s
bz0000 w
1y
0x
0u
1l
0m
b10000100 (
b10000100 A
b10000100 ]
b1 [
b10011 \
0!
#275000
b0 p
1!
#280000
bz {
b0 o
0y
1d
0l
1n
b1001000 (
b1001000 A
b1001000 ]
b10 [
b1 \
0!
#285000
b10110000 v
b0 $
b0 e
b0 q
b0 f
1!
#290000
b10110000 #
b10110000 .
b10110000 8
b10110000 9
b10110000 =
b10110000 g
b10110000 r
b10110000 s
b10110000 w
bz o
1x
1u
0d
0n
1m
b100010010 (
b100010010 A
b100010010 ]
b10011 [
b10 \
0!
#295000
b1011 [
b1011 %
b1011 ?
b1011 z
b10110000 |
b1 p
1!
#300000
b10 k
b10 c
b10 #
b10 .
b10 8
b10 9
b10 =
b10 g
b10 r
b10 s
b10 w
1i
0x
0u
17
0m
b10000100000 (
b10000100000 A
b10000100000 ]
b1 [
b1011 \
0!
#305000
b10 '
b10 h
b10 j
1!
#310000
b1 k
b1 c
bz0001 #
bz0001 .
bz0001 8
bz0001 9
bz0001 =
bz0001 g
bz0001 r
bz0001 s
bz0001 w
b1 o
0i
1d
07
1n
b1001000 (
b1001000 A
b1001000 ]
b10 [
b1 \
0!
#315000
b1000000 v
b1 $
b1 e
b1 q
b1 f
1!
#320000
b0 k
b0 c
b1000000 #
b1000000 .
b1000000 8
b1000000 9
b1000000 =
b1000000 g
b1000000 r
b1000000 s
b1000000 w
bz o
1x
1u
0d
0n
1m
b100010010 (
b100010010 A
b100010010 ]
b1011 [
b10 \
0!
#325000
b1101 [
b100 %
b100 ?
b100 z
b10 p
b1000000 |
1!
#330000
b11 3
bz k
bz c
bz #
bz .
bz 8
bz 9
bz =
bz g
bz r
bz s
bz w
1^
0x
0u
1-
b10 /
0m
b100100000000000000 (
b100100000000000000 A
b100100000000000000 ]
b1110 [
b1101 \
0!
#335000
1!
#340000
b11 k
b11 c
b11 #
b11 .
b11 8
b11 9
b11 =
b11 g
b11 r
b11 s
b11 w
0^
0-
1,
b0 /
16
b1001000000000000 (
b1001000000000000 A
b1001000000000000 ]
b1 [
b1110 \
0!
#345000
b11 +
b11 2
b11 4
b11 :
1!
#350000
b10 k
b10 c
bz0010 #
bz0010 .
bz0010 8
bz0010 9
bz0010 =
bz0010 g
bz0010 r
bz0010 s
bz0010 w
b10 o
0,
1d
06
1n
b1001000 (
b1001000 A
b1001000 ]
b10 [
b1 \
0!
#355000
b10010100 v
b10 $
b10 e
b10 q
b10 f
1!
#360000
b100 k
b100 c
b10010100 #
b10010100 .
b10010100 8
b10010100 9
b10010100 =
b10010100 g
b10010100 r
b10010100 s
b10010100 w
bz o
1x
1u
0d
0n
1m
b100010010 (
b100010010 A
b100010010 ]
b1101 [
b10 \
0!
#365000
b10110 [
b1001 %
b1001 ?
b1001 z
b11 p
b10010100 |
1!
#370000
bz k
bz c
b0 &
b0 @
b0 a
bz #
bz .
bz 8
bz 9
bz =
bz g
bz r
bz s
bz w
1_
0x
0u
0m
b10000000000000000 (
b10000000000000000 A
b10000000000000000 ]
b1 [
b10110 \
0!
#375000
1!
#380000
b11 k
b11 c
bz &
bz @
bz a
bz0011 #
bz0011 .
bz0011 8
bz0011 9
bz0011 =
bz0011 g
bz0011 r
bz0011 s
bz0011 w
b11 o
0_
1d
1n
b1001000 (
b1001000 A
b1001000 ]
b10 [
b1 \
0!
#385000
b10000000 v
b11 $
b11 e
b11 q
b11 f
1!
#390000
b0 k
b0 c
b10000000 #
b10000000 .
b10000000 8
b10000000 9
b10000000 =
b10000000 g
b10000000 r
b10000000 s
b10000000 w
bz o
1x
1u
0d
0n
1m
b100010010 (
b100010010 A
b100010010 ]
b10110 [
b10 \
0!
#395000
b10011 [
b1000 %
b1000 ?
b1000 z
b10000000 |
b100 p
1!
#400000
b0 {
bz0000 #
bz0000 .
bz0000 8
bz0000 9
bz0000 =
bz0000 g
bz0000 r
bz0000 s
bz0000 w
1y
0x
0u
1l
0m
b10000100 (
b10000100 A
b10000100 ]
b1 [
b10011 \
0!
#405000
b0 p
1!
#410000
bz {
b0 o
0y
1d
0l
1n
b1001000 (
b1001000 A
b1001000 ]
b10 [
b1 \
0!
#415000
b10110000 v
b0 $
b0 e
b0 q
b0 f
1!
#420000
b10110000 #
b10110000 .
b10110000 8
b10110000 9
b10110000 =
b10110000 g
b10110000 r
b10110000 s
b10110000 w
bz o
1x
1u
0d
0n
1m
b100010010 (
b100010010 A
b100010010 ]
b10011 [
b10 \
0!
#425000
b1011 [
b1011 %
b1011 ?
b1011 z
b1 p
b10110000 |
1!
#430000
b11 k
b11 c
b11 #
b11 .
b11 8
b11 9
b11 =
b11 g
b11 r
b11 s
b11 w
1i
0x
0u
17
0m
b10000100000 (
b10000100000 A
b10000100000 ]
b1 [
b1011 \
0!
#435000
b11 '
b11 h
b11 j
1!
#440000
b1 k
b1 c
bz0001 #
bz0001 .
bz0001 8
bz0001 9
bz0001 =
bz0001 g
bz0001 r
bz0001 s
bz0001 w
b1 o
0i
1d
07
1n
b1001000 (
b1001000 A
b1001000 ]
b10 [
b1 \
0!
#445000
b1000000 v
b1 $
b1 e
b1 q
b1 f
1!
#450000
b0 k
b0 c
b1000000 #
b1000000 .
b1000000 8
b1000000 9
b1000000 =
b1000000 g
b1000000 r
b1000000 s
b1000000 w
bz o
1x
1u
0d
0n
1m
b100010010 (
b100010010 A
b100010010 ]
b1011 [
b10 \
0!
#455000
b1101 [
b100 %
b100 ?
b100 z
b1000000 |
b10 p
1!
#460000
b100 3
bz k
bz c
bz #
bz .
bz 8
bz 9
bz =
bz g
bz r
bz s
bz w
1^
0x
0u
1-
b10 /
0m
b100100000000000000 (
b100100000000000000 A
b100100000000000000 ]
b1110 [
b1101 \
0!
#465000
1!
#470000
b100 k
b100 c
b100 #
b100 .
b100 8
b100 9
b100 =
b100 g
b100 r
b100 s
b100 w
0^
0-
1,
b0 /
16
b1001000000000000 (
b1001000000000000 A
b1001000000000000 ]
b1 [
b1110 \
0!
#475000
b100 +
b100 2
b100 4
b100 :
1!
#480000
b10 k
b10 c
bz0010 #
bz0010 .
bz0010 8
bz0010 9
bz0010 =
bz0010 g
bz0010 r
bz0010 s
bz0010 w
b10 o
0,
1d
06
1n
b1001000 (
b1001000 A
b1001000 ]
b10 [
b1 \
0!
#485000
b10010100 v
b10 $
b10 e
b10 q
b10 f
1!
#490000
b100 k
b100 c
b10010100 #
b10010100 .
b10010100 8
b10010100 9
b10010100 =
b10010100 g
b10010100 r
b10010100 s
b10010100 w
bz o
1x
1u
0d
0n
1m
b100010010 (
b100010010 A
b100010010 ]
b1101 [
b10 \
0!
#495000
b10110 [
b1001 %
b1001 ?
b1001 z
b10010100 |
b11 p
1!
#500000
bz k
bz c
b0 &
b0 @
b0 a
bz #
bz .
bz 8
bz 9
bz =
bz g
bz r
bz s
bz w
1_
0x
0u
0m
b10000000000000000 (
b10000000000000000 A
b10000000000000000 ]
b1 [
b10110 \
0!
#505000
1!
