IR/IR.v
`timescale 1ns/1ps

module IR(
    input [7:0]BusIn,
    input clk,rst,IRIn,IROut,
    output [3:0]BusOut,CUIn
);

reg [7:0]temp;

always @(posedge clk or rst) begin

    if (rst == 1'b1)
    temp <= 8'b0000_0000;
    else if( IRIn == 1'b1)
    temp <= BusIn ;
end

assign CUIn = temp[7:4];
assign BusOut = IROut? temp[3:0] : 4'bzzzz ;


endmodule

IR/IRTB.v
`timescale 1ns/1ps
`include "IR.v"

module tb;

    reg [7:0]BusIn;
    reg  clk,rst,IRIn,IROut;
    wire [3:0]BusOut,CUIn;

    IR dut(BusIn,clk,rst,IRIn,IROut,BusOut,CUIn);

always #5 clk = ~clk ; 

initial begin
    {BusIn,clk,rst,IRIn,IROut} <= 0 ;
    $dumpfile("output.vcd");
    $dumpvars(0,tb);
    #100 $finish ; 

end

initial begin

    #7;
    rst <= 1;

    #5;
    rst <= 0;

    #1;
    BusIn <= 8'b0011_0101;
    
    #1;
    IRIn <= 1;
    
    #3;
    IRIn <= 0;

    #4;
    IROut <= 1;
    

end


endmodule

IR/output.vcd
$date
	Fri Jun 28 03:05:12 2024
$end
$version
	Icarus Verilog
$end
$timescale
	1ps
$end
$scope module tb $end
$var wire 4 ! CUIn [3:0] $end
$var wire 4 " BusOut [3:0] $end
$var reg 8 # BusIn [7:0] $end
$var reg 1 $ IRIn $end
$var reg 1 % IROut $end
$var reg 1 & clk $end
$var reg 1 ' rst $end
$scope module dut $end
$var wire 8 ( BusIn [7:0] $end
$var wire 1 $ IRIn $end
$var wire 1 % IROut $end
$var wire 1 & clk $end
$var wire 1 ' rst $end
$var wire 4 ) CUIn [3:0] $end
$var wire 4 * BusOut [3:0] $end
$var reg 8 + temp [7:0] $end
$upscope $end
$upscope $end
$enddefinitions $end
#0
$dumpvars
bx +
bz *
bx )
b0 (
0'
0&
0%
0$
b0 #
bz "
bx !
$end
#5000
1&
#7000
b0 !
b0 )
b0 +
1'
#10000
0&
#12000
0'
#13000
b110101 #
b110101 (
#14000
1$
#15000
b11 !
b11 )
b110101 +
1&
#17000
0$
#20000
0&
#21000
b101 "
b101 *
1%
