Control Unit/ControlUnitFsm.v
`timescale 1ns/1ps

`define LDA  4'b0000
`define STA  4'b0001
`define ADD  4'b0010
`define SUB  4'b0011
`define INCA 4'b0100
`define DECR 4'b0101
`define JMPZ 4'b0110
`define NOP  4'b0111
`define JMP  4'b1000
`define JMPC 4'b1001
`define LDI  4'b1010
`define OUT  4'b1011
`define HLT  4'b1100


module controlunit(
    input [3:0]opcode,
    input [1:0]flagReg,
    input clk,rst,
    output [17:0]ControlSignal
);

// Micro Opertions 
parameter idle = 0 ;
// Fetch States
parameter  fetch1 = 1;
parameter  fetch2 = 2; // Internall this state also performs Instruction Decode
                       // Because of Common Bus Architecture
// Load States
parameter  lda1 = 3;
parameter  lda2 = 4;
// Add States
parameter  add1 = 5;
parameter  add2 = 6;
parameter  add3 = 7;
// Subtract States
parameter  sub1 = 8;
parameter  sub2 = 9;
parameter  sub3 = 10;
// Output State
parameter  out  = 11;
// Halt State
parameter  hlt1  = 12;
// Increment States
parameter inc1 = 13;
parameter inc2 = 14;
// Decrement States
parameter dec1 = 15;
parameter dec2 = 16;
// No-Operation State : No additional State is Required : Fetch 1 & 2 are enough

// Store States
parameter sta1 = 17;
parameter sta2 = 18;

// Jump States
parameter jmp1 = 19;

// Jump if Zero States
parameter jmpz1 = 20;
parameter jmpz2 = 21;

// Jump if Carry States
parameter jmpc1 = 22;
parameter jmpc2 = 23;

// Load Immediate States
parameter ldi1 = 24;



reg [17:0]temp ;

reg [4:0]state,nstate;

always @(negedge clk ) begin
    if(rst == 1'b1)
    state <= idle;
    else
    state <= nstate;
end

always@(state) begin
    case(state)
    idle :   temp <= 0 ;
    fetch1 : temp <= 18'h00048;
    fetch2 : temp <= 18'h00112;

    lda1   : temp <= 18'h000C0;
    lda2   : temp <= 18'h01002;

    add1   : temp <= 18'h000C0;
    add2   : temp <= 18'h20202;
    add3   : temp <= 18'h09000;

    sub1   : temp <= 18'h000C0;
    sub2   : temp <= 18'h22202;
    sub3   : temp <= 18'h09000;

    out    : temp <= 18'h00420;

    hlt1   : temp <= 18'h00000;

    inc1   : temp <= 18'h24000;
    inc2   : temp <= 18'h09000;

    dec1   : temp <= 18'h26000;
    dec2   : temp <= 18'h09000;

    sta1   : temp <= 18'h000C0;
    sta2   : temp <= 18'h00201;

    jmp1   : temp <= 18'h00084;

    jmpz1  : temp <= 18'h10000;
    jmpz2  : temp <= 18'h00084;

    jmpc1  : temp <= 18'h10000;
    jmpc2  : temp <= 18'h00084;

    ldi1   : temp <= 18'h00880;

    default : temp <= 0;

    endcase

end



always @(state,opcode,flagReg)begin
    case(state)
    idle : begin
        nstate = fetch1 ;
    end
    fetch1 : begin
        nstate = fetch2 ;
    end
    fetch2 : begin
        case(opcode)
        `LDA : nstate = lda1 ;
        `ADD : nstate = add1 ;
        `SUB : nstate = sub1 ;
        `OUT : nstate = out ;
        `HLT : nstate = hlt1 ;
        `STA : nstate = sta1;
        `INCA: nstate = inc1;
        `DECR: nstate = dec1;
        `JMP : nstate = jmp1 ;
        `JMPZ: nstate = jmpz1;
        `JMPC: nstate = jmpc1;
        `NOP : nstate = fetch1;
        `LDI : nstate = ldi1 ;
        default: nstate = idle;
       endcase

    end
    lda1 : begin
        nstate = lda2 ;

    end
    lda2 : begin
        nstate = fetch1 ;
    end
    add1 : begin
        nstate = add2;

    end
    add2 : begin
        nstate = add3 ;

    end
    add3 : begin
        nstate = fetch1;
    end
    sub1 : begin
        nstate = sub2;
    end
    sub2 : begin
        nstate = sub3 ;
    end
    sub3 : begin
        nstate = fetch1;
    end

    out : begin
        nstate = fetch1;
    end

    hlt1 : begin
        if(rst == 1'b1)
        nstate = idle;
        else 
        nstate = hlt1 ;
    end

    sta1 : begin
        nstate = sta2;
    end
    sta2 : begin
        nstate = fetch1;
    end

    inc1 : begin 
        nstate = inc2 ;
    end
    inc2 : begin
        nstate = fetch1;
    end

    dec1 : begin
        nstate = dec2 ;
    end
    dec2 : begin
        nstate = fetch1;
    end

    jmp1 : begin
        nstate = fetch1 ;
    end
    jmpz1: begin
        if(flagReg[1] == 1'b1)
        nstate = jmpz2;
        else
        nstate = fetch1 ;
    end

    jmpz2 : begin
        nstate = fetch1;
    end
    jmpc1: begin
        if(flagReg[0] == 1'b1)
        nstate = jmpc2;
        else
        nstate = fetch1 ;
    end
    jmpc2 : begin
        nstate = fetch1;
    end
    
    ldi1 : begin
        nstate = fetch1;

    end

    default : nstate = idle ;

    endcase
    
end

assign ControlSignal = temp ;



endmodule

Control Unit/ControlUnitFsmTB.v
`timescale 1ns/1ps
`include "ControlUnitFsm.v"

`define LDA  4'b0000
`define STA  4'b0001
`define ADD  4'b0010
`define SUB  4'b0011
`define INCA 4'b0100
`define DECR 4'b0101
`define JMPZ 4'b0110
`define NOP  4'b0111
`define JMP  4'b1000
`define JMPC 4'b1001
`define LDI  4'b1010
`define OUT  4'b1011
`define HLT  4'b1100

module tb;

reg [3:0]opcode;
reg [1:0]flagReg;
reg clk,rst;
wire [17:0]ControlSignal;


controlunit dut(opcode,flagReg,clk,rst,ControlSignal);

always #5 clk = ~clk ; 

initial begin
    {opcode,flagReg,clk,rst} <= 0 ;
    $dumpfile("output.vcd");
    $dumpvars(0,tb);
    #1000 $finish ; 

end


initial begin

// Reset Logic : Reset signal High : 3 <= t <= 12
// This Resets all the Registers on posedge clk and CU on negedge clk

#3;
rst = 1;
#9;
rst = 0;

end

initial begin

// Opcode Logic : Opcode may change on positive edge of clk in decode/f2 phase of every instruction

#20; // Reset and Idle State
#15; // Fetch1 and Fetch2(Half) states

opcode = `LDA;

#5;  // Fetch2 Completed

#20 // LDA : 2 States 


#15; // Fetch1 and Fetch2(Half) states

opcode = `STA;

#5;  // Fetch2 Completed

#20 // STA : 2 States 

#15; // Fetch1 and Fetch2(Half) states

opcode = `ADD;

#5;  // Fetch2 Completed

#30 // ADD : 3 States

#15; // Fetch1 and Fetch2(Half) states

opcode = `SUB;

#5;  // Fetch2 Completed

#30 // SUB : 3 States

#15; // Fetch1 and Fetch2(Half) states

opcode = `INCA;

#5;  // Fetch2 Completed

#20 // INCA : 2 States 

#15; // Fetch1 and Fetch2(Half) states

opcode = `DECR;

#5;  // Fetch2 Completed

#20 // DECR : 2 States 

// JMPZ : Conditional Jump : Based on Flag Zero
// Testbench : First Without Jump and then With Jump 

#15; // Fetch1 and Fetch2(Half) states

opcode = `JMPZ;

#5;  // Fetch2 Completed

// Flag Zero = 0 : No Jump

#10 // JMPZ : 1 States : No Jump

#15; // Fetch1 and Fetch2(Half) states

opcode = `JMPZ;

#5;  // Fetch2 Completed

#5;  // Flag Out & Flag High

flagReg = 2'b10;

#5; // Decision made : Jumpz to be performed

#10 ; // JMPZ : 1 States : Jump

#15; // Fetch1 and Fetch2(Half) states

opcode = `NOP;

#5;  // Fetch2 Completed

// No Additional State in NOP : Perform next fetch

// JMP : Unconditional Jump 

#15; // Fetch1 and Fetch2(Half) states

opcode = `JMP;

#5;  // Fetch2 Completed

#10 //  JMP : 1-State





// JMPC : Conditional Jump : Based on Flag Carry
// Testbench : First Without Jump and then With Jump 

#15; // Fetch1 and Fetch2(Half) states

opcode = `JMPC;

#5;  // Fetch2 Completed

// Flag Carry = 0 : No Jump

#10 // JMPC : 1 States : No Jump

#15; // Fetch1 and Fetch2(Half) states

opcode = `JMPC;

#5;  // Fetch2 Completed

#5;  // Flag Out & Flag High

flagReg = 2'b11;

#5; // Decision made : Jumpc to be performed

#10 ; // JMPC : 1 States : Jump



#15; // Fetch1 and Fetch2(Half) states

opcode = `LDI;

#5;  // Fetch2 Completed

#10; // LDI : 1-State


#15; // Fetch1 and Fetch2(Half) states

opcode = `OUT;

#5;  // Fetch2 Completed

#10; // OUT : 1-State


#15; // Fetch1 and Fetch2(Half) states

opcode = `HLT;

#5;  // Fetch2 Completed

#10; //  


#20; 
rst <= 1;

#10;
rst <= 0;











end




endmodule

Control Unit/output.vcd
$date
	Thu Jul  4 15:39:59 2024
$end
$version
	Icarus Verilog
$end
$timescale
	1ps
$end
$scope module tb $end
$var wire 18 ! ControlSignal [17:0] $end
$var reg 1 " clk $end
$var reg 2 # flagReg [1:0] $end
$var reg 4 $ opcode [3:0] $end
$var reg 1 % rst $end
$scope module dut $end
$var wire 18 & ControlSignal [17:0] $end
$var wire 1 " clk $end
$var wire 2 ' flagReg [1:0] $end
$var wire 4 ( opcode [3:0] $end
$var wire 1 % rst $end
$var parameter 32 ) add1 $end
$var parameter 32 * add2 $end
$var parameter 32 + add3 $end
$var parameter 32 , dec1 $end
$var parameter 32 - dec2 $end
$var parameter 32 . fetch1 $end
$var parameter 32 / fetch2 $end
$var parameter 32 0 hlt1 $end
$var parameter 32 1 idle $end
$var parameter 32 2 inc1 $end
$var parameter 32 3 inc2 $end
$var parameter 32 4 jmp1 $end
$var parameter 32 5 jmpc1 $end
$var parameter 32 6 jmpc2 $end
$var parameter 32 7 jmpz1 $end
$var parameter 32 8 jmpz2 $end
$var parameter 32 9 lda1 $end
$var parameter 32 : lda2 $end
$var parameter 32 ; ldi1 $end
$var parameter 32 < out $end
$var parameter 32 = sta1 $end
$var parameter 32 > sta2 $end
$var parameter 32 ? sub1 $end
$var parameter 32 @ sub2 $end
$var parameter 32 A sub3 $end
$var reg 5 B nstate [4:0] $end
$var reg 5 C state [4:0] $end
$var reg 18 D temp [17:0] $end
$upscope $end
$upscope $end
$enddefinitions $end
$comment Show the parameter values. $end
$dumpall
b1010 A
b1001 @
b1000 ?
b10010 >
b10001 =
b1011 <
b11000 ;
b100 :
b11 9
b10101 8
b10100 7
b10111 6
b10110 5
b10011 4
b1110 3
b1101 2
b0 1
b1100 0
b10 /
b1 .
b10000 -
b1111 ,
b111 +
b110 *
b101 )
$end
#0
$dumpvars
bx D
bx C
b0 B
b0 (
b0 '
bx &
0%
b0 $
b0 #
0"
bx !
$end
#3000
1%
#5000
1"
#10000
b0 !
b0 &
b0 D
b1 B
b0 C
0"
#12000
0%
#15000
1"
#20000
b1001000 !
b1001000 &
b1001000 D
b10 B
b1 C
0"
#25000
1"
#30000
b100010010 !
b100010010 &
b100010010 D
b11 B
b10 C
0"
#35000
1"
#40000
b11000000 !
b11000000 &
b11000000 D
b100 B
b11 C
0"
#45000
1"
#50000
b1000000000010 !
b1000000000010 &
b1000000000010 D
b1 B
b100 C
0"
#55000
1"
#60000
b1001000 !
b1001000 &
b1001000 D
b10 B
b1 C
0"
#65000
1"
#70000
b100010010 !
b100010010 &
b100010010 D
b11 B
b10 C
0"
#75000
b10001 B
1"
b1 $
b1 (
#80000
b11000000 !
b11000000 &
b11000000 D
b10010 B
b10001 C
0"
#85000
1"
#90000
b1000000001 !
b1000000001 &
b1000000001 D
b1 B
b10010 C
0"
#95000
1"
#100000
b1001000 !
b1001000 &
b1001000 D
b10 B
b1 C
0"
#105000
1"
#110000
b100010010 !
b100010010 &
b100010010 D
b10001 B
b10 C
0"
#115000
b101 B
1"
b10 $
b10 (
#120000
b11000000 !
b11000000 &
b11000000 D
b110 B
b101 C
0"
#125000
1"
#130000
b100000001000000010 !
b100000001000000010 &
b100000001000000010 D
b111 B
b110 C
0"
#135000
1"
#140000
b1001000000000000 !
b1001000000000000 &
b1001000000000000 D
b1 B
b111 C
0"
#145000
1"
#150000
b1001000 !
b1001000 &
b1001000 D
b10 B
b1 C
0"
#155000
1"
#160000
b100010010 !
b100010010 &
b100010010 D
b101 B
b10 C
0"
#165000
b1000 B
1"
b11 $
b11 (
#170000
b11000000 !
b11000000 &
b11000000 D
b1001 B
b1000 C
0"
#175000
1"
#180000
b100010001000000010 !
b100010001000000010 &
b100010001000000010 D
b1010 B
b1001 C
0"
#185000
1"
#190000
b1001000000000000 !
b1001000000000000 &
b1001000000000000 D
b1 B
b1010 C
0"
#195000
1"
#200000
b1001000 !
b1001000 &
b1001000 D
b10 B
b1 C
0"
#205000
1"
#210000
b100010010 !
b100010010 &
b100010010 D
b1000 B
b10 C
0"
#215000
b1101 B
1"
b100 $
b100 (
#220000
b100100000000000000 !
b100100000000000000 &
b100100000000000000 D
b1110 B
b1101 C
0"
#225000
1"
#230000
b1001000000000000 !
b1001000000000000 &
b1001000000000000 D
b1 B
b1110 C
0"
#235000
1"
#240000
b1001000 !
b1001000 &
b1001000 D
b10 B
b1 C
0"
#245000
1"
#250000
b100010010 !
b100010010 &
b100010010 D
b1101 B
b10 C
0"
#255000
b1111 B
1"
b101 $
b101 (
#260000
b100110000000000000 !
b100110000000000000 &
b100110000000000000 D
b10000 B
b1111 C
0"
#265000
1"
#270000
b1001000000000000 !
b1001000000000000 &
b1001000000000000 D
b1 B
b10000 C
0"
#275000
1"
#280000
b1001000 !
b1001000 &
b1001000 D
b10 B
b1 C
0"
#285000
1"
#290000
b100010010 !
b100010010 &
b100010010 D
b1111 B
b10 C
0"
#295000
b10100 B
1"
b110 $
b110 (
#300000
b10000000000000000 !
b10000000000000000 &
b10000000000000000 D
b1 B
b10100 C
0"
#305000
1"
#310000
b1001000 !
b1001000 &
b1001000 D
b10 B
b1 C
0"
#315000
1"
#320000
b100010010 !
b100010010 &
b100010010 D
b10100 B
b10 C
0"
#325000
1"
#330000
b10000000000000000 !
b10000000000000000 &
b10000000000000000 D
b1 B
b10100 C
0"
#335000
b10101 B
1"
b10 #
b10 '
#340000
b10000100 !
b10000100 &
b10000100 D
b1 B
b10101 C
0"
#345000
1"
#350000
b1001000 !
b1001000 &
b1001000 D
b10 B
b1 C
0"
#355000
1"
#360000
b100010010 !
b100010010 &
b100010010 D
b10100 B
b10 C
0"
#365000
b1 B
1"
b111 $
b111 (
#370000
b1001000 !
b1001000 &
b1001000 D
b10 B
b1 C
0"
#375000
1"
#380000
b100010010 !
b100010010 &
b100010010 D
b1 B
b10 C
0"
#385000
b10011 B
1"
b1000 $
b1000 (
#390000
b10000100 !
b10000100 &
b10000100 D
b1 B
b10011 C
0"
#395000
1"
#400000
b1001000 !
b1001000 &
b1001000 D
b10 B
b1 C
0"
#405000
1"
#410000
b100010010 !
b100010010 &
b100010010 D
b10011 B
b10 C
0"
#415000
b10110 B
1"
b1001 $
b1001 (
#420000
b10000000000000000 !
b10000000000000000 &
b10000000000000000 D
b1 B
b10110 C
0"
#425000
1"
#430000
b1001000 !
b1001000 &
b1001000 D
b10 B
b1 C
0"
#435000
1"
#440000
b100010010 !
b100010010 &
b100010010 D
b10110 B
b10 C
0"
#445000
1"
#450000
b10000000000000000 !
b10000000000000000 &
b10000000000000000 D
b1 B
b10110 C
0"
#455000
b10111 B
1"
b11 #
b11 '
#460000
b10000100 !
b10000100 &
b10000100 D
b1 B
b10111 C
0"
#465000
1"
#470000
b1001000 !
b1001000 &
b1001000 D
b10 B
b1 C
0"
#475000
1"
#480000
b100010010 !
b100010010 &
b100010010 D
b10110 B
b10 C
0"
#485000
b11000 B
1"
b1010 $
b1010 (
#490000
b100010000000 !
b100010000000 &
b100010000000 D
b1 B
b11000 C
0"
#495000
1"
#500000
b1001000 !
b1001000 &
b1001000 D
b10 B
b1 C
0"
#505000
1"
#510000
b100010010 !
b100010010 &
b100010010 D
b11000 B
b10 C
0"
#515000
b1011 B
1"
b1011 $
b1011 (
#520000
b10000100000 !
b10000100000 &
b10000100000 D
b1 B
b1011 C
0"
#525000
1"
#530000
b1001000 !
b1001000 &
b1001000 D
b10 B
b1 C
0"
#535000
1"
#540000
b100010010 !
b100010010 &
b100010010 D
b1011 B
b10 C
0"
#545000
b1100 B
1"
b1100 $
b1100 (
#550000
b0 !
b0 &
b0 D
b1100 C
0"
#555000
1"
#560000
0"
#565000
1"
#570000
0"
#575000
1"
#580000
1%
0"
#585000
1"
#590000
b1 B
b0 C
0%
0"
#595000
1"
#600000
b1001000 !
b1001000 &
b1001000 D
b10 B
b1 C
0"
#605000
1"
#610000
b100010010 !
b100010010 &
b100010010 D
b1100 B
b10 C
0"
#615000
1"
#620000
b0 !
b0 &
b0 D
b1100 C
0"
