PC/PC.v
`timescale 1ns/1ps

module PC(
    input [3:0]BusIn,
    input clk,rst,PCInc,PCOut,PCIn,
    output [3:0]BusOut
);

reg [3:0]temp;

always @(posedge clk or rst) begin

    if(rst ==1'b1)
    temp <= 4'b0000;
    else if(PCInc == 1'b1)
    temp <= temp + 1;
    else if(PCIn == 1'b1)
    temp <= BusIn;

end

assign BusOut = PCOut ? temp : 4'bzzzz;



endmodule

PC/PCTB.v
`timescale 1ns/1ps
`include "PC.v"

module tb;

reg [3:0]BusIn;
reg clk,rst,PCInc,PCOut,PCIn;
wire [3:0]BusOut;

PC dut( BusIn, clk,rst,PCInc,PCOut,PCIn,BusOut);

always #5 clk = ~clk ; 

initial
begin
    {clk,rst,PCInc,PCIn,BusIn} <= 0 ;
    $dumpfile("output.vcd");
    $dumpvars(0,tb);

    #200 $finish ;

end

initial begin

    #2;
    rst <= 1;

    #5;
    rst <= 0 ;

    #2;
    BusIn <= 4'b0101;

    #3;
    PCIn <= 1;

    #5;
    PCIn <= 0;

    #2;
    PCInc <= 1 ;

    #20;
    PCInc <= 0 ;

    #2;
    PCOut <= 1;

end

endmodule

PC/output.vcd
$date
	Sat Jun 29 00:23:07 2024
$end
$version
	Icarus Verilog
$end
$timescale
	1ps
$end
$scope module tb $end
$var wire 4 ! BusOut [3:0] $end
$var reg 4 " BusIn [3:0] $end
$var reg 1 # PCIn $end
$var reg 1 $ PCInc $end
$var reg 1 % PCOut $end
$var reg 1 & clk $end
$var reg 1 ' rst $end
$scope module dut $end
$var wire 4 ( BusIn [3:0] $end
$var wire 1 # PCIn $end
$var wire 1 $ PCInc $end
$var wire 1 % PCOut $end
$var wire 1 & clk $end
$var wire 1 ' rst $end
$var wire 4 ) BusOut [3:0] $end
$var reg 4 * temp [3:0] $end
$upscope $end
$upscope $end
$enddefinitions $end
#0
$dumpvars
bx *
bx )
b0 (
0'
0&
x%
0$
0#
b0 "
bx !
$end
#2000
b0 *
1'
#5000
1&
#7000
0'
#9000
b101 "
b101 (
#10000
0&
#12000
1#
#15000
b101 *
1&
#17000
0#
#19000
1$
#20000
0&
#25000
b110 *
1&
#30000
0&
#35000
b111 *
1&
#39000
0$
#40000
0&
#41000
b111 !
b111 )
1%
