ALU/ALU.v
`timescale 1ns/1ps

`define ADD 2'b00
`define SUB 2'b01
`define INC 2'b10
`define DCR 2'b11


module ALU(
    input [7:0]Accumulator,BRegister,
    input [1:0]Operation,
    input ALUOut,
    output [7:0]BusOut,
    output [1:0]Flags
);

reg [8:0]result;

always@(*) begin

    case(Operation) 
    `ADD : result <= Accumulator + BRegister ;
    `SUB : result <= Accumulator - BRegister ;
    `INC : result <= Accumulator + 1 ;
    `DCR : result <= Accumulator - 1 ;
    default : result <= result ;

    endcase

end

assign BusOut = ALUOut ? result[7:0] : 8'bzzzz_zzzz;
assign Flags = {~|result[7:0],result[8]};  // Zero,Carry


endmodule

ALU/ALUTB.v
`timescale 1ns/1ps
`include "ALU.v"

module tb;

    reg [7:0]Accumulator,BRegister;
    reg [1:0]Operation;
    reg ALUOut;
    wire [7:0]BusOut;
    wire [1:0]Flags;

    ALU dut(Accumulator,BRegister,Operation,ALUOut,BusOut,Flags);

    initial begin
        {Accumulator,BRegister,Operation,ALUOut} <= 0;
        $dumpfile("output.vcd");
        $dumpvars(0,tb);
        #100 $finish ; 

    end


    initial begin
    #5;
    Accumulator <= 6;
    BRegister   <= 2;
    Operation <= 0;
    #2;
    ALUOut    <= 1;
    #2
    ALUOut   <= 0;
    #2;
    Operation <= 1;
        #2;
    ALUOut    <= 1;
    #2
    ALUOut   <= 0;
    #2;
    Operation <= 2;
        #2;
    ALUOut    <= 1;
    #2
    ALUOut   <= 0;
    #2;
    Operation <= 3;
    ALUOut    <= 1;
    #2
    ALUOut   <= 0;
    
end



endmodule

ALU/output.vcd
$date
	Sun Jun 30 10:05:55 2024
$end
$version
	Icarus Verilog
$end
$timescale
	1ps
$end
$scope module tb $end
$var wire 2 ! Flags [1:0] $end
$var wire 8 " BusOut [7:0] $end
$var reg 1 # ALUOut $end
$var reg 8 $ Accumulator [7:0] $end
$var reg 8 % BRegister [7:0] $end
$var reg 2 & Operation [1:0] $end
$scope module dut $end
$var wire 1 # ALUOut $end
$var wire 8 ' Accumulator [7:0] $end
$var wire 8 ( BRegister [7:0] $end
$var wire 2 ) Operation [1:0] $end
$var wire 2 * Flags [1:0] $end
$var wire 8 + BusOut [7:0] $end
$var reg 9 , result [8:0] $end
$upscope $end
$upscope $end
$enddefinitions $end
$comment Show the parameter values. $end
$dumpall
$end
#0
$dumpvars
b0 ,
bz +
b10 *
b0 )
b0 (
b0 '
b0 &
b0 %
b0 $
0#
bz "
b10 !
$end
#5000
b0 !
b0 *
b1000 ,
b10 %
b10 (
b110 $
b110 '
#7000
b1000 "
b1000 +
1#
#9000
bz "
bz +
0#
#11000
b100 ,
b1 &
b1 )
#13000
b100 "
b100 +
1#
#15000
bz "
bz +
0#
#17000
b111 ,
b10 &
b10 )
#19000
b111 "
b111 +
1#
#21000
bz "
bz +
0#
#23000
b101 ,
b101 "
b101 +
1#
b11 &
b11 )
#25000
bz "
bz +
0#
