Accumulator/Accumulator.v
`timescale 1ns/1ps

module Accumulator(
    input [7:0]BusIn,
    input clk,rst,Ain,ALowerIn,Aout,
    output [7:0]BusOut,ALUIn
);

reg [7:0]temp;
always @(posedge clk,rst) begin
    if(rst == 1'b1)
    temp <= 8'b0000_0000;
    else if (Ain == 1'b1)
    temp <= BusIn ;
    else if (ALowerIn == 1'b1)
    temp <= {4'b0000,BusIn[3:0]};

end

assign BusOut = Aout ? temp : 8'bzzzz_zzzz;
assign ALUIn  = temp ; 
    

endmodule

Accumulator/AccumulatorTB.v
`timescale 1ns/1ps
`include "Accumulator.v"

module tb;

reg [7:0]BusIn;
reg clk,rst,Ain,ALowerIn,Aout;
wire [7:0] BusOut, ALUIn ;

Accumulator dut(BusIn,clk,rst,Ain,ALowerIn,Aout,BusOut,ALUIn);

always #5 clk = ~clk ; 

initial begin

{BusIn,clk,Ain,Aout,rst} = 0;
$dumpfile("output.vcd");
$dumpvars(0,tb);

#100 $finish ; 

end

initial begin

    #12 ;
    rst <= 1;

    #5;
    rst <= 0;

    #2;
    BusIn <= 8'b0101_1100;

    #3;
    Ain <= 1;

    #10;
    Ain <= 0;

    #2;
    Aout <= 1;
    
    #5;
    Aout <= 0;

    #5;
    rst <= 1;

    #3;
    rst <= 0;

    #3;
    BusIn <= 8'b1101_1110;

    #2;
    ALowerIn <= 1;

    #10;
    ALowerIn <= 0;

    #2;
    Aout <= 1;


end



endmodule

Accumulator/output.vcd
$date
	Fri Jun 28 01:24:33 2024
$end
$version
	Icarus Verilog
$end
$timescale
	1ps
$end
$scope module tb $end
$var wire 8 ! BusOut [7:0] $end
$var wire 8 " ALUIn [7:0] $end
$var reg 1 # ALowerIn $end
$var reg 1 $ Ain $end
$var reg 1 % Aout $end
$var reg 8 & BusIn [7:0] $end
$var reg 1 ' clk $end
$var reg 1 ( rst $end
$scope module dut $end
$var wire 8 ) ALUIn [7:0] $end
$var wire 1 # ALowerIn $end
$var wire 1 $ Ain $end
$var wire 1 % Aout $end
$var wire 8 * BusIn [7:0] $end
$var wire 1 ' clk $end
$var wire 1 ( rst $end
$var wire 8 + BusOut [7:0] $end
$var reg 8 , temp [7:0] $end
$upscope $end
$upscope $end
$enddefinitions $end
#0
$dumpvars
bx ,
bz +
b0 *
bx )
0(
0'
b0 &
0%
0$
x#
bx "
bz !
$end
#5000
1'
#10000
0'
#12000
b0 "
b0 )
b0 ,
1(
#15000
1'
#17000
0(
#19000
b1011100 &
b1011100 *
#20000
0'
#22000
1$
#25000
b1011100 "
b1011100 )
b1011100 ,
1'
#30000
0'
#32000
0$
#34000
b1011100 !
b1011100 +
1%
#35000
1'
#39000
bz !
bz +
0%
#40000
0'
#44000
b0 "
b0 )
b0 ,
1(
#45000
1'
#47000
0(
#50000
b11011110 &
b11011110 *
0'
#52000
1#
#55000
b1110 "
b1110 )
b1110 ,
1'
#60000
0'
#62000
0#
#64000
b1110 !
b1110 +
1%
